{
    "file_type" : "MMC-TRANSLATION-INDEX",
    "version" : 2,
    "languages" : {
        "ar" : {
            "file" : "70d6e86e6847e093606e2088a8e08c78baf2ff54.class",
            "sha1" : "70d6e86e6847e093606e2088a8e08c78baf2ff54",
            "size" : 89309,
            "translated" : 725,
            "fuzzy" : 56,
            "untranslated" : 380
        },
        "bg" : {
            "file" : "4e33cdcfef11f9fe7ffb5ea8e219e76af6ac8dc6.class",
            "sha1" : "4e33cdcfef11f9fe7ffb5ea8e219e76af6ac8dc6",
            "size" : 41925,
            "translated" : 323,
            "fuzzy" : 88,
            "untranslated" : 750
        },
        "ca" : {
            "file" : "7178a9ca15b6e90bd5d953e9a0c393ec56e08b7a.class",
            "sha1" : "7178a9ca15b6e90bd5d953e9a0c393ec56e08b7a",
            "size" : 73867,
            "translated" : 540,
            "fuzzy" : 64,
            "untranslated" : 557
        },
        "cs" : {
            "file" : "11d077cbf02ade3e00ffb527c60c4c5cd7869bba.class",
            "sha1" : "11d077cbf02ade3e00ffb527c60c4c5cd7869bba",
            "size" : 115499,
            "translated" : 880,
            "fuzzy" : 56,
            "untranslated" : 225
        },
        "cy" : {
            "file" : "76eb0412167a02dfd2704653ca833c3773d3d39d.class",
            "sha1" : "76eb0412167a02dfd2704653ca833c3773d3d39d",
            "size" : 16727,
            "translated" : 99,
            "fuzzy" : 50,
            "untranslated" : 1012
        },
        "da" : {
            "file" : "1e5cb470c01e5ce104ea5653a4f9f693f4d7a7e2.class",
            "sha1" : "1e5cb470c01e5ce104ea5653a4f9f693f4d7a7e2",
            "size" : 74181,
            "translated" : 489,
            "fuzzy" : 127,
            "untranslated" : 545
        },
        "de" : {
            "file" : "7f53641194ec9fc44513ca9b7d020374b829c494.class",
            "sha1" : "7f53641194ec9fc44513ca9b7d020374b829c494",
            "size" : 161114,
            "translated" : 1088,
            "fuzzy" : 21,
            "untranslated" : 52
        },
        "de_CH" : {
            "file" : "2eee7dd3d056776ddb420beee09194ecee970ce3.class",
            "sha1" : "2eee7dd3d056776ddb420beee09194ecee970ce3",
            "size" : 112240,
            "translated" : 792,
            "fuzzy" : 60,
            "untranslated" : 309
        },
        "el" : {
            "file" : "2c9fb67d2c29abd88a5628e357e052662a5b72a4.class",
            "sha1" : "2c9fb67d2c29abd88a5628e357e052662a5b72a4",
            "size" : 121786,
            "translated" : 845,
            "fuzzy" : 57,
            "untranslated" : 259
        },
        "en_GB" : {
            "file" : "01ab195ecc1587f775da4a800e0aebbc42b65130.class",
            "sha1" : "01ab195ecc1587f775da4a800e0aebbc42b65130",
            "size" : 140248,
            "translated" : 1037,
            "fuzzy" : 34,
            "untranslated" : 90
        },
        "eo" : {
            "file" : "874b6b8f7ff85fd576307046db60a8d8d725dbd9.class",
            "sha1" : "874b6b8f7ff85fd576307046db60a8d8d725dbd9",
            "size" : 23215,
            "translated" : 207,
            "fuzzy" : 55,
            "untranslated" : 899
        },
        "es" : {
            "file" : "3b1b4b8a4b4475f358ea89a75a844175e6c6f541.class",
            "sha1" : "3b1b4b8a4b4475f358ea89a75a844175e6c6f541",
            "size" : 152886,
            "translated" : 997,
            "fuzzy" : 51,
            "untranslated" : 113
        },
        "es_UY" : {
            "file" : "b10251db892e8c1390780e18503a9a366736d997.class",
            "sha1" : "b10251db892e8c1390780e18503a9a366736d997",
            "size" : 137366,
            "translated" : 924,
            "fuzzy" : 62,
            "untranslated" : 175
        },
        "et" : {
            "file" : "9749b907f01c4116975b5050cb32798c297b8231.class",
            "sha1" : "9749b907f01c4116975b5050cb32798c297b8231",
            "size" : 103510,
            "translated" : 807,
            "fuzzy" : 59,
            "untranslated" : 295
        },
        "fa" : {
            "file" : "808784e2101c55b6e2bba72b1dc386fdd443692e.class",
            "sha1" : "808784e2101c55b6e2bba72b1dc386fdd443692e",
            "size" : 110812,
            "translated" : 845,
            "fuzzy" : 55,
            "untranslated" : 261
        },
        "fi" : {
            "file" : "1ca3d916dbb8137fa8acf14a56fe7e41c6639993.class",
            "sha1" : "1ca3d916dbb8137fa8acf14a56fe7e41c6639993",
            "size" : 110380,
            "translated" : 813,
            "fuzzy" : 60,
            "untranslated" : 288
        },
        "fr" : {
            "file" : "9a98c3a0b43557bd8cc3eed7853f3b2234c9acb0.class",
            "sha1" : "9a98c3a0b43557bd8cc3eed7853f3b2234c9acb0",
            "size" : 149113,
            "translated" : 954,
            "fuzzy" : 59,
            "untranslated" : 148
        },
        "gl" : {
            "file" : "da0532e4440e53e6d750c93ec5cd709b84377f93.class",
            "sha1" : "da0532e4440e53e6d750c93ec5cd709b84377f93",
            "size" : 112284,
            "translated" : 806,
            "fuzzy" : 58,
            "untranslated" : 297
        },
        "he" : {
            "file" : "7ec702623e072be5042422093b26d173cb96bc2a.class",
            "sha1" : "7ec702623e072be5042422093b26d173cb96bc2a",
            "size" : 64108,
            "translated" : 565,
            "fuzzy" : 76,
            "untranslated" : 520
        },
        "hu" : {
            "file" : "43a9031d50c68a96f20b488a3b52e2e1ce69c2ba.class",
            "sha1" : "43a9031d50c68a96f20b488a3b52e2e1ce69c2ba",
            "size" : 93698,
            "translated" : 700,
            "fuzzy" : 52,
            "untranslated" : 409
        },
        "hy" : {
            "file" : "222eacd4438eef78b7a3653c399c43428eee68b3.class",
            "sha1" : "222eacd4438eef78b7a3653c399c43428eee68b3",
            "size" : 7034,
            "translated" : 93,
            "fuzzy" : 16,
            "untranslated" : 1052
        },
        "id" : {
            "file" : "0e2873baf3965397ae740da167e51841d75507a5.class",
            "sha1" : "0e2873baf3965397ae740da167e51841d75507a5",
            "size" : 118325,
            "translated" : 863,
            "fuzzy" : 61,
            "untranslated" : 237
        },
        "is" : {
            "file" : "956bcd5df67dc03dc603258d5b2529ccbca5f588.class",
            "sha1" : "956bcd5df67dc03dc603258d5b2529ccbca5f588",
            "size" : 12555,
            "translated" : 132,
            "fuzzy" : 39,
            "untranslated" : 990
        },
        "it" : {
            "file" : "859c122d2e92a23d7650017b6cf21402cbf8fa46.class",
            "sha1" : "859c122d2e92a23d7650017b6cf21402cbf8fa46",
            "size" : 141793,
            "translated" : 951,
            "fuzzy" : 58,
            "untranslated" : 152
        },
        "ja" : {
            "file" : "d700ae373b8043774ea5c689710fc9cc2fecbecc.class",
            "sha1" : "d700ae373b8043774ea5c689710fc9cc2fecbecc",
            "size" : 87486,
            "translated" : 802,
            "fuzzy" : 62,
            "untranslated" : 297
        },
        "ja_KANJI" : {
            "file" : "33a4218fcac2fb5f0966d0d407c72f7a022de0fc.class",
            "sha1" : "33a4218fcac2fb5f0966d0d407c72f7a022de0fc",
            "size" : 95061,
            "translated" : 865,
            "fuzzy" : 55,
            "untranslated" : 241
        },
        "ka" : {
            "file" : "bfff3e5b04d96f90964bd20bd9ffa0f47c4a8574.class",
            "sha1" : "bfff3e5b04d96f90964bd20bd9ffa0f47c4a8574",
            "size" : 3639,
            "translated" : 25,
            "fuzzy" : 16,
            "untranslated" : 1120
        },
        "ko" : {
            "file" : "45c1075b5e5997c4de5555766bb761162f7c4d24.class",
            "sha1" : "45c1075b5e5997c4de5555766bb761162f7c4d24",
            "size" : 104005,
            "translated" : 925,
            "fuzzy" : 57,
            "untranslated" : 179
        },
        "lb" : {
            "file" : "9464dca2cf1ffcec0c0a15fec613b3ea3afc8f23.class",
            "sha1" : "9464dca2cf1ffcec0c0a15fec613b3ea3afc8f23",
            "size" : 27081,
            "translated" : 147,
            "fuzzy" : 84,
            "untranslated" : 930
        },
        "lt" : {
            "file" : "14cc1ed373465716d143b798429af856d6f72239.class",
            "sha1" : "14cc1ed373465716d143b798429af856d6f72239",
            "size" : 29140,
            "translated" : 221,
            "fuzzy" : 88,
            "untranslated" : 852
        },
        "lv" : {
            "file" : "a370ef3ad44529626c034078b656c437a1b71cd3.class",
            "sha1" : "a370ef3ad44529626c034078b656c437a1b71cd3",
            "size" : 86802,
            "translated" : 662,
            "fuzzy" : 71,
            "untranslated" : 428
        },
        "lzh" : {
            "file" : "ef7674b520887d6764461f10343028c9de0fa768.class",
            "sha1" : "ef7674b520887d6764461f10343028c9de0fa768",
            "size" : 2101,
            "translated" : 19,
            "fuzzy" : 1,
            "untranslated" : 1089
        },
        "mk" : {
            "file" : "941e242fe0ab9c0c42e63f63c8b5d8e6418b15c0.class",
            "sha1" : "941e242fe0ab9c0c42e63f63c8b5d8e6418b15c0",
            "size" : 15439,
            "translated" : 78,
            "fuzzy" : 68,
            "untranslated" : 1015
        },
        "nb" : {
            "file" : "52f74fc5e2247c763848155cac7699d865da911e.class",
            "sha1" : "52f74fc5e2247c763848155cac7699d865da911e",
            "size" : 67761,
            "translated" : 579,
            "fuzzy" : 60,
            "untranslated" : 522
        },
        "nl" : {
            "file" : "b6cbc24614cb3795cbbfc84e6bda1edddd4ead66.class",
            "sha1" : "b6cbc24614cb3795cbbfc84e6bda1edddd4ead66",
            "size" : 153803,
            "translated" : 1020,
            "fuzzy" : 63,
            "untranslated" : 78
        },
        "nn" : {
            "file" : "304d2ea2bed5b15905ef6f7db9e066b8f8f52385.class",
            "sha1" : "304d2ea2bed5b15905ef6f7db9e066b8f8f52385",
            "size" : 127529,
            "translated" : 923,
            "fuzzy" : 61,
            "untranslated" : 177
        },
        "pl" : {
            "file" : "15be445da70e62ff58d4094f4806797d9f6aaf3e.class",
            "sha1" : "15be445da70e62ff58d4094f4806797d9f6aaf3e",
            "size" : 151120,
            "translated" : 1056,
            "fuzzy" : 28,
            "untranslated" : 77
        },
        "pt_PT" : {
            "file" : "319978b0e056163115d88c664a5b57cd9468d1e1.class",
            "sha1" : "319978b0e056163115d88c664a5b57cd9468d1e1",
            "size" : 134374,
            "translated" : 925,
            "fuzzy" : 58,
            "untranslated" : 178
        },
        "pt_BR" : {
            "file" : "c2cf3c2310960fd57532263502224cd84ebe1dc3.class",
            "sha1" : "c2cf3c2310960fd57532263502224cd84ebe1dc3",
            "size" : 156925,
            "translated" : 1097,
            "fuzzy" : 17,
            "untranslated" : 47
        },
        "ro" : {
            "file" : "9d2b88d31ea5934898d7c57cc9a6f991d0a6fe58.class",
            "sha1" : "9d2b88d31ea5934898d7c57cc9a6f991d0a6fe58",
            "size" : 58808,
            "translated" : 406,
            "fuzzy" : 94,
            "untranslated" : 661
        },
        "ru" : {
            "file" : "ba6cebc7cbfaf9f3add63c17e4d4415fddbcf401.class",
            "sha1" : "ba6cebc7cbfaf9f3add63c17e4d4415fddbcf401",
            "size" : 154745,
            "translated" : 1115,
            "fuzzy" : 4,
            "untranslated" : 42
        },
        "si" : {
            "file" : "870a6d0607c73e4de8d84e7e22d2b40fa2a8585b.class",
            "sha1" : "870a6d0607c73e4de8d84e7e22d2b40fa2a8585b",
            "size" : 1836,
            "translated" : 10,
            "fuzzy" : 19,
            "untranslated" : 1132
        },
        "sk" : {
            "file" : "be36834bd2021885e65ee7df8b199ddcedb2e0e4.class",
            "sha1" : "be36834bd2021885e65ee7df8b199ddcedb2e0e4",
            "size" : 112033,
            "translated" : 848,
            "fuzzy" : 55,
            "untranslated" : 258
        },
        "sl" : {
            "file" : "c758b80aaffce5f4ff0a391a40ad3f26d6a9c6eb.class",
            "sha1" : "c758b80aaffce5f4ff0a391a40ad3f26d6a9c6eb",
            "size" : 20669,
            "translated" : 108,
            "fuzzy" : 70,
            "untranslated" : 983
        },
        "sr" : {
            "file" : "15704d63038b4e67e9df8e83e2bce622ad081c64.class",
            "sha1" : "15704d63038b4e67e9df8e83e2bce622ad081c64",
            "size" : 7227,
            "translated" : 41,
            "fuzzy" : 29,
            "untranslated" : 1091
        },
        "sv" : {
            "file" : "ffec478e97e90203024d6a34fc98c23f82aa55d4.class",
            "sha1" : "ffec478e97e90203024d6a34fc98c23f82aa55d4",
            "size" : 113693,
            "translated" : 855,
            "fuzzy" : 56,
            "untranslated" : 250
        },
        "th" : {
            "file" : "4d785c5828a52173f45fbfbb464716499f5255a5.class",
            "sha1" : "4d785c5828a52173f45fbfbb464716499f5255a5",
            "size" : 31627,
            "translated" : 242,
            "fuzzy" : 59,
            "untranslated" : 860
        },
        "tr" : {
            "file" : "6c89c30fe598b5ab844433080cc4a39c5c8b08b6.class",
            "sha1" : "6c89c30fe598b5ab844433080cc4a39c5c8b08b6",
            "size" : 135586,
            "translated" : 971,
            "fuzzy" : 49,
            "untranslated" : 141
        },
        "uk" : {
            "file" : "949de633eecc632c2a897ab782d0d89669f6d3af.class",
            "sha1" : "949de633eecc632c2a897ab782d0d89669f6d3af",
            "size" : 117597,
            "translated" : 855,
            "fuzzy" : 56,
            "untranslated" : 250
        },
        "vi" : {
            "file" : "e087472b05d529da18c277d6325967a4a46a141c.class",
            "sha1" : "e087472b05d529da18c277d6325967a4a46a141c",
            "size" : 129688,
            "translated" : 924,
            "fuzzy" : 61,
            "untranslated" : 176
        },
        "zh" : {
            "file" : "c7689bffa9bce18ea3f39e05a90e4bf0e0240a33.class",
            "sha1" : "c7689bffa9bce18ea3f39e05a90e4bf0e0240a33",
            "size" : 106170,
            "translated" : 1053,
            "fuzzy" : 28,
            "untranslated" : 80
        },
        "zh_TW" : {
            "file" : "7beef4fc8f21a6f067b042ad9171bdee5dc29894.class",
            "sha1" : "7beef4fc8f21a6f067b042ad9171bdee5dc29894",
            "size" : 97858,
            "translated" : 966,
            "fuzzy" : 64,
            "untranslated" : 131
        }
    }
}
