{
    "file_type" : "MMC-TRANSLATION-INDEX",
    "version" : 2,
    "languages" : {
        "ar" : {
            "file" : "b858fa74cd871d31a147184ff4ac4ede4607424b.class",
            "sha1" : "b858fa74cd871d31a147184ff4ac4ede4607424b",
            "size" : 90722,
            "translated" : 670,
            "fuzzy" : 127,
            "untranslated" : 708
        },
        "az" : {
            "file" : "d468e7202681b92d0503fd0a1c78d759d01d5c35.class",
            "sha1" : "d468e7202681b92d0503fd0a1c78d759d01d5c35",
            "size" : 5669,
            "translated" : 29,
            "fuzzy" : 6,
            "untranslated" : 1470
        },
        "bg" : {
            "file" : "04d667cd4476ec4c7aaa061074d630d3fd1c64b1.class",
            "sha1" : "04d667cd4476ec4c7aaa061074d630d3fd1c64b1",
            "size" : 49526,
            "translated" : 332,
            "fuzzy" : 139,
            "untranslated" : 1034
        },
        "ca" : {
            "file" : "4414bcb05f91c12403f5006506c232605cc348fb.class",
            "sha1" : "4414bcb05f91c12403f5006506c232605cc348fb",
            "size" : 168921,
            "translated" : 1107,
            "fuzzy" : 67,
            "untranslated" : 331
        },
        "cs" : {
            "file" : "9cfd0983e8a2739d9d8e7254f0eb7c4485408f38.class",
            "sha1" : "9cfd0983e8a2739d9d8e7254f0eb7c4485408f38",
            "size" : 212524,
            "translated" : 1505,
            "fuzzy" : 0,
            "untranslated" : 0
        },
        "cy" : {
            "file" : "90384e5944d393d1474412ed598bbcfedbdf3c09.class",
            "sha1" : "90384e5944d393d1474412ed598bbcfedbdf3c09",
            "size" : 16811,
            "translated" : 82,
            "fuzzy" : 68,
            "untranslated" : 1355
        },
        "da" : {
            "file" : "b3dd71844dd26299be47a48a6b7dd01be3b5db85.class",
            "sha1" : "b3dd71844dd26299be47a48a6b7dd01be3b5db85",
            "size" : 121959,
            "translated" : 874,
            "fuzzy" : 13,
            "untranslated" : 618
        },
        "de" : {
            "file" : "d8b64be4227a55ed04e51930a5cc98c53cdc9318.class",
            "sha1" : "d8b64be4227a55ed04e51930a5cc98c53cdc9318",
            "size" : 227358,
            "translated" : 1505,
            "fuzzy" : 0,
            "untranslated" : 0
        },
        "de_CH" : {
            "file" : "61d0bfabfa98012abcb6d8d0df8725f1d11d4121.class",
            "sha1" : "61d0bfabfa98012abcb6d8d0df8725f1d11d4121",
            "size" : 110434,
            "translated" : 707,
            "fuzzy" : 140,
            "untranslated" : 658
        },
        "el" : {
            "file" : "6a2006880ab9908e925e0c8144417c49f8bf94e6.class",
            "sha1" : "6a2006880ab9908e925e0c8144417c49f8bf94e6",
            "size" : 120662,
            "translated" : 755,
            "fuzzy" : 141,
            "untranslated" : 609
        },
        "en@pirate" : {
            "file" : "4fd2c9a12f1691600f3e00a0b0e986efab4a5116.class",
            "sha1" : "4fd2c9a12f1691600f3e00a0b0e986efab4a5116",
            "size" : 16598,
            "translated" : 115,
            "fuzzy" : 12,
            "untranslated" : 1378
        },
        "en@uwu" : {
            "file" : "55a8cdad661bb4d9e3c581256d7e7bec52485e67.class",
            "sha1" : "55a8cdad661bb4d9e3c581256d7e7bec52485e67",
            "size" : 95667,
            "translated" : 474,
            "fuzzy" : 139,
            "untranslated" : 892
        },
        "en_AU" : {
            "file" : "5acb267c656db0dfba020a858f3b34f2b5d9cec1.class",
            "sha1" : "5acb267c656db0dfba020a858f3b34f2b5d9cec1",
            "size" : 209106,
            "translated" : 1505,
            "fuzzy" : 0,
            "untranslated" : 0
        },
        "en_CA" : {
            "file" : "c256fea3f1f62cc8880f67d844b18c6977608123.class",
            "sha1" : "c256fea3f1f62cc8880f67d844b18c6977608123",
            "size" : 50684,
            "translated" : 288,
            "fuzzy" : 92,
            "untranslated" : 1125
        },
        "en_GB" : {
            "file" : "a76cee93fbbb068a77b98d266c378a2270c70a00.class",
            "sha1" : "a76cee93fbbb068a77b98d266c378a2270c70a00",
            "size" : 203511,
            "translated" : 1479,
            "fuzzy" : 2,
            "untranslated" : 24
        },
        "en_NZ" : {
            "file" : "4884fd9af6890647b7af1aefa57f38cca49ad899.class",
            "sha1" : "4884fd9af6890647b7af1aefa57f38cca49ad899",
            "size" : 16,
            "translated" : 0,
            "fuzzy" : 0,
            "untranslated" : 1505
        },
        "eo" : {
            "file" : "5d250d94a22f18fa20f0a0070e15d69bb6f6977e.class",
            "sha1" : "5d250d94a22f18fa20f0a0070e15d69bb6f6977e",
            "size" : 39253,
            "translated" : 280,
            "fuzzy" : 93,
            "untranslated" : 1132
        },
        "es" : {
            "file" : "ab493982b432b050665eff64c8a68c66b380072c.class",
            "sha1" : "ab493982b432b050665eff64c8a68c66b380072c",
            "size" : 227000,
            "translated" : 1505,
            "fuzzy" : 0,
            "untranslated" : 0
        },
        "es_UY" : {
            "file" : "2287bd30b6b2fb8f20132700228828631f5b3420.class",
            "sha1" : "2287bd30b6b2fb8f20132700228828631f5b3420",
            "size" : 150650,
            "translated" : 1042,
            "fuzzy" : 21,
            "untranslated" : 442
        },
        "et" : {
            "file" : "d8b8d27a75711b8fa02129af3afa8d910cf1d04a.class",
            "sha1" : "d8b8d27a75711b8fa02129af3afa8d910cf1d04a",
            "size" : 147945,
            "translated" : 1165,
            "fuzzy" : 36,
            "untranslated" : 304
        },
        "eu" : {
            "file" : "881e930db1e770404f317554ecb5c65c536ba678.class",
            "sha1" : "881e930db1e770404f317554ecb5c65c536ba678",
            "size" : 11993,
            "translated" : 76,
            "fuzzy" : 49,
            "untranslated" : 1380
        },
        "fa" : {
            "file" : "7db30cb4a1d7ae7b0227ec6f72d2fb6cea843a82.class",
            "sha1" : "7db30cb4a1d7ae7b0227ec6f72d2fb6cea843a82",
            "size" : 107434,
            "translated" : 737,
            "fuzzy" : 143,
            "untranslated" : 625
        },
        "fi" : {
            "file" : "c7d9d385a00aa5fa33ae92133136b313232fbcb2.class",
            "sha1" : "c7d9d385a00aa5fa33ae92133136b313232fbcb2",
            "size" : 118043,
            "translated" : 880,
            "fuzzy" : 77,
            "untranslated" : 548
        },
        "fil" : {
            "file" : "cfd3f0b01452d3575c9989ad87a283e890386dd1.class",
            "sha1" : "cfd3f0b01452d3575c9989ad87a283e890386dd1",
            "size" : 31,
            "translated" : 0,
            "fuzzy" : 0,
            "untranslated" : 1505
        },
        "fr" : {
            "file" : "88f973426ebe2c0e9bb0a4e1a1f2ed8ba497979e.class",
            "sha1" : "88f973426ebe2c0e9bb0a4e1a1f2ed8ba497979e",
            "size" : 229015,
            "translated" : 1479,
            "fuzzy" : 2,
            "untranslated" : 24
        },
        "gl" : {
            "file" : "a29b8194a40c56054bdc07e6e08ce92b9b1bcf0b.class",
            "sha1" : "a29b8194a40c56054bdc07e6e08ce92b9b1bcf0b",
            "size" : 110139,
            "translated" : 714,
            "fuzzy" : 139,
            "untranslated" : 652
        },
        "he" : {
            "file" : "d639a00c26e1331da478607ce7417604949dfb1c.class",
            "sha1" : "d639a00c26e1331da478607ce7417604949dfb1c",
            "size" : 62771,
            "translated" : 494,
            "fuzzy" : 142,
            "untranslated" : 869
        },
        "hr" : {
            "file" : "172f2cc1cb45c2ce412680ac2b6d2e4563c1323b.class",
            "sha1" : "172f2cc1cb45c2ce412680ac2b6d2e4563c1323b",
            "size" : 9605,
            "translated" : 42,
            "fuzzy" : 6,
            "untranslated" : 1457
        },
        "hu" : {
            "file" : "07d30a1530dc419b1fbae410d672d0e25bacf4dc.class",
            "sha1" : "07d30a1530dc419b1fbae410d672d0e25bacf4dc",
            "size" : 222109,
            "translated" : 1500,
            "fuzzy" : 0,
            "untranslated" : 5
        },
        "hy" : {
            "file" : "15ac878d7338e956ea63f933386e623790c7e0f9.class",
            "sha1" : "15ac878d7338e956ea63f933386e623790c7e0f9",
            "size" : 7651,
            "translated" : 84,
            "fuzzy" : 34,
            "untranslated" : 1387
        },
        "id" : {
            "file" : "aa3ac3a7a4d430b7ef3c286473b8862c097f3b5f.class",
            "sha1" : "aa3ac3a7a4d430b7ef3c286473b8862c097f3b5f",
            "size" : 129884,
            "translated" : 813,
            "fuzzy" : 203,
            "untranslated" : 489
        },
        "is" : {
            "file" : "448b64f733aa63ecbe124c4ad2187d51abc1107e.class",
            "sha1" : "448b64f733aa63ecbe124c4ad2187d51abc1107e",
            "size" : 12851,
            "translated" : 120,
            "fuzzy" : 56,
            "untranslated" : 1329
        },
        "it" : {
            "file" : "6c8f73e74d712477e1b0cd69d6c872b86a83daea.class",
            "sha1" : "6c8f73e74d712477e1b0cd69d6c872b86a83daea",
            "size" : 220201,
            "translated" : 1479,
            "fuzzy" : 2,
            "untranslated" : 24
        },
        "ja" : {
            "file" : "bd64abdc748babd48514829910f9af5b3e931039.class",
            "sha1" : "bd64abdc748babd48514829910f9af5b3e931039",
            "size" : 97434,
            "translated" : 859,
            "fuzzy" : 92,
            "untranslated" : 554
        },
        "ja_KANJI" : {
            "file" : "e30be077e631e9681acd6716dc99b61afb360cb2.class",
            "sha1" : "e30be077e631e9681acd6716dc99b61afb360cb2",
            "size" : 92430,
            "translated" : 768,
            "fuzzy" : 130,
            "untranslated" : 607
        },
        "ka" : {
            "file" : "ee463660e910e97785463070f5e966604784621b.class",
            "sha1" : "ee463660e910e97785463070f5e966604784621b",
            "size" : 3642,
            "translated" : 19,
            "fuzzy" : 22,
            "untranslated" : 1464
        },
        "kk" : {
            "file" : "dbfaa7abc238c6baed6edb53539ee939fef127e6.class",
            "sha1" : "dbfaa7abc238c6baed6edb53539ee939fef127e6",
            "size" : 4968,
            "translated" : 22,
            "fuzzy" : 8,
            "untranslated" : 1475
        },
        "ko" : {
            "file" : "e0f586e8d302cebbfb1ed906417b3155dd30dee7.class",
            "sha1" : "e0f586e8d302cebbfb1ed906417b3155dd30dee7",
            "size" : 152371,
            "translated" : 1304,
            "fuzzy" : 70,
            "untranslated" : 131
        },
        "lb" : {
            "file" : "da93aae43e7bebb2eb08222b0ef2a71f6c6152be.class",
            "sha1" : "da93aae43e7bebb2eb08222b0ef2a71f6c6152be",
            "size" : 27305,
            "translated" : 131,
            "fuzzy" : 105,
            "untranslated" : 1269
        },
        "lt" : {
            "file" : "26f4a63778e5c25ef6eb288446784a5e235cf439.class",
            "sha1" : "26f4a63778e5c25ef6eb288446784a5e235cf439",
            "size" : 40664,
            "translated" : 265,
            "fuzzy" : 119,
            "untranslated" : 1121
        },
        "lv" : {
            "file" : "eae5384f69b54eb33527603a8047f59bed1c38d4.class",
            "sha1" : "eae5384f69b54eb33527603a8047f59bed1c38d4",
            "size" : 87255,
            "translated" : 592,
            "fuzzy" : 147,
            "untranslated" : 766
        },
        "mk" : {
            "file" : "a510caf16f0b38e6d0ed62a202c983a1fe95c115.class",
            "sha1" : "a510caf16f0b38e6d0ed62a202c983a1fe95c115",
            "size" : 35924,
            "translated" : 189,
            "fuzzy" : 95,
            "untranslated" : 1221
        },
        "nan" : {
            "file" : "857732089df80f1c97f66edd7c074e6e98623692.class",
            "sha1" : "857732089df80f1c97f66edd7c074e6e98623692",
            "size" : 15352,
            "translated" : 158,
            "fuzzy" : 0,
            "untranslated" : 1243
        },
        "nb" : {
            "file" : "7212b6c0998259c4de425008420438fc67655122.class",
            "sha1" : "7212b6c0998259c4de425008420438fc67655122",
            "size" : 75777,
            "translated" : 573,
            "fuzzy" : 125,
            "untranslated" : 807
        },
        "nl" : {
            "file" : "462864bd24e0620d395270172d6d704bca5fd104.class",
            "sha1" : "462864bd24e0620d395270172d6d704bca5fd104",
            "size" : 200589,
            "translated" : 1339,
            "fuzzy" : 42,
            "untranslated" : 124
        },
        "nn" : {
            "file" : "64a2dee1f3ad4c5781a407c640186f87c6a866b5.class",
            "sha1" : "64a2dee1f3ad4c5781a407c640186f87c6a866b5",
            "size" : 123023,
            "translated" : 803,
            "fuzzy" : 156,
            "untranslated" : 546
        },
        "pl" : {
            "file" : "63b0dcab6740ec088d4f8243c3934bac2cfa357e.class",
            "sha1" : "63b0dcab6740ec088d4f8243c3934bac2cfa357e",
            "size" : 221532,
            "translated" : 1505,
            "fuzzy" : 0,
            "untranslated" : 0
        },
        "pt_PT" : {
            "file" : "0c1fa4ae148a04f79a6454781b85ad3f46bc88ec.class",
            "sha1" : "0c1fa4ae148a04f79a6454781b85ad3f46bc88ec",
            "size" : 133700,
            "translated" : 827,
            "fuzzy" : 155,
            "untranslated" : 523
        },
        "pt_BR" : {
            "file" : "71debba37e53605839975965474e3cee306417ed.class",
            "sha1" : "71debba37e53605839975965474e3cee306417ed",
            "size" : 219770,
            "translated" : 1505,
            "fuzzy" : 0,
            "untranslated" : 0
        },
        "qu" : {
            "file" : "373982fa808dcd9778f6c5ea7c1c1c946df7a0ef.class",
            "sha1" : "373982fa808dcd9778f6c5ea7c1c1c946df7a0ef",
            "size" : 30,
            "translated" : 0,
            "fuzzy" : 0,
            "untranslated" : 1505
        },
        "ro" : {
            "file" : "6ccab2960608a71a2081004f7b298270d3408803.class",
            "sha1" : "6ccab2960608a71a2081004f7b298270d3408803",
            "size" : 84587,
            "translated" : 478,
            "fuzzy" : 182,
            "untranslated" : 845
        },
        "ru" : {
            "file" : "fc4f7dd7bc2a042dd3dc7fa67d5ad09dede7aad9.class",
            "sha1" : "fc4f7dd7bc2a042dd3dc7fa67d5ad09dede7aad9",
            "size" : 215029,
            "translated" : 1499,
            "fuzzy" : 3,
            "untranslated" : 3
        },
        "si" : {
            "file" : "1e24a7b87c1749afa7a623062461fbdc437ae3a6.class",
            "sha1" : "1e24a7b87c1749afa7a623062461fbdc437ae3a6",
            "size" : 2131,
            "translated" : 9,
            "fuzzy" : 25,
            "untranslated" : 1471
        },
        "sk" : {
            "file" : "63f8eb1f3602d77b68ef6539257af87b5a0c17bd.class",
            "sha1" : "63f8eb1f3602d77b68ef6539257af87b5a0c17bd",
            "size" : 108697,
            "translated" : 746,
            "fuzzy" : 138,
            "untranslated" : 621
        },
        "sl" : {
            "file" : "e56f9d49046152d01aa514723585833bcbdb70b3.class",
            "sha1" : "e56f9d49046152d01aa514723585833bcbdb70b3",
            "size" : 41670,
            "translated" : 234,
            "fuzzy" : 117,
            "untranslated" : 1154
        },
        "sq" : {
            "file" : "4844b91079d0819e122877a0b784703ee4a1dbba.class",
            "sha1" : "4844b91079d0819e122877a0b784703ee4a1dbba",
            "size" : 30,
            "translated" : 0,
            "fuzzy" : 0,
            "untranslated" : 1505
        },
        "sr" : {
            "file" : "0be1c409fcb2fd4d815a7d9ddc9f730970ffff22.class",
            "sha1" : "0be1c409fcb2fd4d815a7d9ddc9f730970ffff22",
            "size" : 7505,
            "translated" : 27,
            "fuzzy" : 46,
            "untranslated" : 1432
        },
        "sv" : {
            "file" : "1c51b4815f49164741fd3480711a17f025dcf1a5.class",
            "sha1" : "1c51b4815f49164741fd3480711a17f025dcf1a5",
            "size" : 216650,
            "translated" : 1505,
            "fuzzy" : 0,
            "untranslated" : 0
        },
        "th" : {
            "file" : "9f5821d065859be709601fe5bd4b0b5d615170b0.class",
            "sha1" : "9f5821d065859be709601fe5bd4b0b5d615170b0",
            "size" : 39952,
            "translated" : 273,
            "fuzzy" : 111,
            "untranslated" : 1121
        },
        "tok" : {
            "file" : "8a0f74d43ec65915039cd81804b7f488eb64a024.class",
            "sha1" : "8a0f74d43ec65915039cd81804b7f488eb64a024",
            "size" : 386,
            "translated" : 5,
            "fuzzy" : 0,
            "untranslated" : 1382
        },
        "tr" : {
            "file" : "8f23e7174482d422626159696f8870684844e8a0.class",
            "sha1" : "8f23e7174482d422626159696f8870684844e8a0",
            "size" : 208860,
            "translated" : 1479,
            "fuzzy" : 2,
            "untranslated" : 24
        },
        "uk" : {
            "file" : "a1ce26689dae8e2311eb55ed227028b3ca9b57b8.class",
            "sha1" : "a1ce26689dae8e2311eb55ed227028b3ca9b57b8",
            "size" : 175942,
            "translated" : 1201,
            "fuzzy" : 74,
            "untranslated" : 230
        },
        "vi" : {
            "file" : "5bb8171bacd63a262f68b03ec53e1a089b612372.class",
            "sha1" : "5bb8171bacd63a262f68b03ec53e1a089b612372",
            "size" : 156355,
            "translated" : 1000,
            "fuzzy" : 144,
            "untranslated" : 361
        },
        "zh" : {
            "file" : "17ca3bb35010d8248e60d4881ec8e2843c137501.class",
            "sha1" : "17ca3bb35010d8248e60d4881ec8e2843c137501",
            "size" : 150634,
            "translated" : 1479,
            "fuzzy" : 2,
            "untranslated" : 24
        },
        "zh_TW" : {
            "file" : "8a245e68e79708b848bca776f018aaff8164a6dc.class",
            "sha1" : "8a245e68e79708b848bca776f018aaff8164a6dc",
            "size" : 151377,
            "translated" : 1486,
            "fuzzy" : 5,
            "untranslated" : 14
        }
    }
}
