{
    "file_type" : "MMC-TRANSLATION-INDEX",
    "version" : 2,
    "languages" : {
        "ar" : {
            "file" : "fd94507921c3bd821fce997dfc98c14feaa52a02.class",
            "sha1" : "fd94507921c3bd821fce997dfc98c14feaa52a02",
            "size" : 92431,
            "translated" : 754,
            "fuzzy" : 54,
            "untranslated" : 306
        },
        "be" : {
            "file" : "e89314048a141037530dd0ccb31cf0de7a756187.class",
            "sha1" : "e89314048a141037530dd0ccb31cf0de7a756187",
            "size" : 34,
            "translated" : 0,
            "fuzzy" : 0,
            "untranslated" : 1114
        },
        "bg" : {
            "file" : "875a262abd6ac688d3ae3ecd88776b9f7d36a2f2.class",
            "sha1" : "875a262abd6ac688d3ae3ecd88776b9f7d36a2f2",
            "size" : 43166,
            "translated" : 345,
            "fuzzy" : 84,
            "untranslated" : 685
        },
        "ca" : {
            "file" : "bde14f81aa74aab841def615e73069fd3f788113.class",
            "sha1" : "bde14f81aa74aab841def615e73069fd3f788113",
            "size" : 76172,
            "translated" : 565,
            "fuzzy" : 60,
            "untranslated" : 489
        },
        "cs" : {
            "file" : "745daed5cf482636e18115d35631a9a56c9302c7.class",
            "sha1" : "745daed5cf482636e18115d35631a9a56c9302c7",
            "size" : 118885,
            "translated" : 918,
            "fuzzy" : 46,
            "untranslated" : 150
        },
        "cy" : {
            "file" : "021fb2d1c0c9bcfa0363a3d815f556a7b4953b9b.class",
            "sha1" : "021fb2d1c0c9bcfa0363a3d815f556a7b4953b9b",
            "size" : 16341,
            "translated" : 102,
            "fuzzy" : 45,
            "untranslated" : 967
        },
        "da" : {
            "file" : "1deaaf1813e4b2a923102ab402ee645dca312160.class",
            "sha1" : "1deaaf1813e4b2a923102ab402ee645dca312160",
            "size" : 76408,
            "translated" : 518,
            "fuzzy" : 118,
            "untranslated" : 478
        },
        "de" : {
            "file" : "18b467e5ded80a9895dd5c10f9da0045fb8a4b62.class",
            "sha1" : "18b467e5ded80a9895dd5c10f9da0045fb8a4b62",
            "size" : 157163,
            "translated" : 1084,
            "fuzzy" : 25,
            "untranslated" : 5
        },
        "de_CH" : {
            "file" : "67abb3da0d5673b59df51044f7831a356f614243.class",
            "sha1" : "67abb3da0d5673b59df51044f7831a356f614243",
            "size" : 115544,
            "translated" : 829,
            "fuzzy" : 50,
            "untranslated" : 235
        },
        "el" : {
            "file" : "bdb3154e1d6a7e18e59887df441286b7ff56ab31.class",
            "sha1" : "bdb3154e1d6a7e18e59887df441286b7ff56ab31",
            "size" : 124909,
            "translated" : 882,
            "fuzzy" : 45,
            "untranslated" : 187
        },
        "en_GB" : {
            "file" : "889c0efc68f48247576945fae94aba1efbc26538.class",
            "sha1" : "889c0efc68f48247576945fae94aba1efbc26538",
            "size" : 113621,
            "translated" : 867,
            "fuzzy" : 53,
            "untranslated" : 194
        },
        "eo" : {
            "file" : "d3f6ded273ddccffd50009b7a424af649a6518ce.class",
            "sha1" : "d3f6ded273ddccffd50009b7a424af649a6518ce",
            "size" : 24508,
            "translated" : 221,
            "fuzzy" : 59,
            "untranslated" : 834
        },
        "es" : {
            "file" : "25cfdccb7ed0411b45b54f2249edefc2f673e1a2.class",
            "sha1" : "25cfdccb7ed0411b45b54f2249edefc2f673e1a2",
            "size" : 151389,
            "translated" : 1012,
            "fuzzy" : 42,
            "untranslated" : 60
        },
        "es_UY" : {
            "file" : "d558fdaf04e900d10f68f93b117e3c36278e7753.class",
            "sha1" : "d558fdaf04e900d10f68f93b117e3c36278e7753",
            "size" : 141020,
            "translated" : 964,
            "fuzzy" : 50,
            "untranslated" : 100
        },
        "et" : {
            "file" : "ed696d2eb2689f7675766e1b092aa6ec7e8be7be.class",
            "sha1" : "ed696d2eb2689f7675766e1b092aa6ec7e8be7be",
            "size" : 106862,
            "translated" : 847,
            "fuzzy" : 47,
            "untranslated" : 220
        },
        "fa" : {
            "file" : "e59a152be1aa9160fd8ffe8fce109cacf7f31d87.class",
            "sha1" : "e59a152be1aa9160fd8ffe8fce109cacf7f31d87",
            "size" : 114317,
            "translated" : 885,
            "fuzzy" : 43,
            "untranslated" : 186
        },
        "fi" : {
            "file" : "03131cfb6cf164483c73b1c03772164981450d8d.class",
            "sha1" : "03131cfb6cf164483c73b1c03772164981450d8d",
            "size" : 113548,
            "translated" : 849,
            "fuzzy" : 50,
            "untranslated" : 215
        },
        "fr" : {
            "file" : "4fb5ae8116b8e2ce05c20a72a01f083ffd05fe00.class",
            "sha1" : "4fb5ae8116b8e2ce05c20a72a01f083ffd05fe00",
            "size" : 152645,
            "translated" : 998,
            "fuzzy" : 44,
            "untranslated" : 72
        },
        "gl" : {
            "file" : "22d8b83cecf7d7dcab1652016c83e4b914239670.class",
            "sha1" : "22d8b83cecf7d7dcab1652016c83e4b914239670",
            "size" : 115922,
            "translated" : 843,
            "fuzzy" : 49,
            "untranslated" : 222
        },
        "he" : {
            "file" : "24c9f0e974865f7ddad7e8419a16d74348d0fd93.class",
            "sha1" : "24c9f0e974865f7ddad7e8419a16d74348d0fd93",
            "size" : 65058,
            "translated" : 597,
            "fuzzy" : 62,
            "untranslated" : 455
        },
        "hu" : {
            "file" : "f968743ad67c3afd133af0ce60d362af808dff1d.class",
            "sha1" : "f968743ad67c3afd133af0ce60d362af808dff1d",
            "size" : 96862,
            "translated" : 729,
            "fuzzy" : 48,
            "untranslated" : 337
        },
        "hy" : {
            "file" : "c8bdfa8b6a01f9d18151fd683771373328957287.class",
            "sha1" : "c8bdfa8b6a01f9d18151fd683771373328957287",
            "size" : 7497,
            "translated" : 96,
            "fuzzy" : 20,
            "untranslated" : 998
        },
        "id" : {
            "file" : "d3e445010b7118d72490c48454cbbb51e59c99d6.class",
            "sha1" : "d3e445010b7118d72490c48454cbbb51e59c99d6",
            "size" : 121634,
            "translated" : 903,
            "fuzzy" : 47,
            "untranslated" : 164
        },
        "is" : {
            "file" : "c843ab67a7c333b3e3952a92504a35d627fb6421.class",
            "sha1" : "c843ab67a7c333b3e3952a92504a35d627fb6421",
            "size" : 13765,
            "translated" : 152,
            "fuzzy" : 36,
            "untranslated" : 926
        },
        "it" : {
            "file" : "9e56740a07bcca74fe1ad9651132d904da9d9be4.class",
            "sha1" : "9e56740a07bcca74fe1ad9651132d904da9d9be4",
            "size" : 146032,
            "translated" : 996,
            "fuzzy" : 43,
            "untranslated" : 75
        },
        "ja" : {
            "file" : "c44b58bdb87f5aac6ff883d7bb4e1b250bda806f.class",
            "sha1" : "c44b58bdb87f5aac6ff883d7bb4e1b250bda806f",
            "size" : 90414,
            "translated" : 840,
            "fuzzy" : 52,
            "untranslated" : 222
        },
        "ja_KANJI" : {
            "file" : "de2d01e452ba47657074578214865751e72d970f.class",
            "sha1" : "de2d01e452ba47657074578214865751e72d970f",
            "size" : 97838,
            "translated" : 903,
            "fuzzy" : 44,
            "untranslated" : 167
        },
        "jv" : {
            "file" : "4884fd9af6890647b7af1aefa57f38cca49ad899.class",
            "sha1" : "4884fd9af6890647b7af1aefa57f38cca49ad899",
            "size" : 16,
            "translated" : 0,
            "fuzzy" : 0,
            "untranslated" : 1114
        },
        "ka" : {
            "file" : "bfff3e5b04d96f90964bd20bd9ffa0f47c4a8574.class",
            "sha1" : "bfff3e5b04d96f90964bd20bd9ffa0f47c4a8574",
            "size" : 3639,
            "translated" : 25,
            "fuzzy" : 16,
            "untranslated" : 1073
        },
        "kn" : {
            "file" : "2aa2d42c51f9cf024e3777f0dde4270388fd22ae.class",
            "sha1" : "2aa2d42c51f9cf024e3777f0dde4270388fd22ae",
            "size" : 23,
            "translated" : 0,
            "fuzzy" : 0,
            "untranslated" : 1114
        },
        "ko" : {
            "file" : "7090fa655ab3444ac3b64b83fa90a9da3b5150cf.class",
            "sha1" : "7090fa655ab3444ac3b64b83fa90a9da3b5150cf",
            "size" : 106802,
            "translated" : 965,
            "fuzzy" : 45,
            "untranslated" : 104
        },
        "lb" : {
            "file" : "3e63c27750e2c9fe89b4dca8f650764cd5540711.class",
            "sha1" : "3e63c27750e2c9fe89b4dca8f650764cd5540711",
            "size" : 27127,
            "translated" : 155,
            "fuzzy" : 78,
            "untranslated" : 881
        },
        "lt" : {
            "file" : "be6a287e49fb71317bfde12de71d3f4286bb9443.class",
            "sha1" : "be6a287e49fb71317bfde12de71d3f4286bb9443",
            "size" : 29637,
            "translated" : 232,
            "fuzzy" : 85,
            "untranslated" : 797
        },
        "lv" : {
            "file" : "d4690f292e0a29d891d15b60dcfbed53d3284874.class",
            "sha1" : "d4690f292e0a29d891d15b60dcfbed53d3284874",
            "size" : 88982,
            "translated" : 694,
            "fuzzy" : 61,
            "untranslated" : 359
        },
        "lzh" : {
            "file" : "ef7674b520887d6764461f10343028c9de0fa768.class",
            "sha1" : "ef7674b520887d6764461f10343028c9de0fa768",
            "size" : 2101,
            "translated" : 19,
            "fuzzy" : 1,
            "untranslated" : 1089
        },
        "mk" : {
            "file" : "9e8b5ae0268fb9856f243de43f1011ec278992f5.class",
            "sha1" : "9e8b5ae0268fb9856f243de43f1011ec278992f5",
            "size" : 15369,
            "translated" : 81,
            "fuzzy" : 65,
            "untranslated" : 968
        },
        "nb" : {
            "file" : "e1d9792f1d868b9a16d839731144ec88ffd3c3dc.class",
            "sha1" : "e1d9792f1d868b9a16d839731144ec88ffd3c3dc",
            "size" : 69014,
            "translated" : 598,
            "fuzzy" : 59,
            "untranslated" : 457
        },
        "nl" : {
            "file" : "2aa16056d8f6045805845382d3dc871520e5f7bd.class",
            "sha1" : "2aa16056d8f6045805845382d3dc871520e5f7bd",
            "size" : 138504,
            "translated" : 965,
            "fuzzy" : 49,
            "untranslated" : 100
        },
        "nn" : {
            "file" : "83ac898d8102eaf6df5cbcd3cc3886248d523f60.class",
            "sha1" : "83ac898d8102eaf6df5cbcd3cc3886248d523f60",
            "size" : 130918,
            "translated" : 964,
            "fuzzy" : 49,
            "untranslated" : 101
        },
        "pl" : {
            "file" : "4b676d226f157b2cf8212ae21276e708f612aa66.class",
            "sha1" : "4b676d226f157b2cf8212ae21276e708f612aa66",
            "size" : 152908,
            "translated" : 1112,
            "fuzzy" : 2,
            "untranslated" : 0
        },
        "pt_PT" : {
            "file" : "6867f45c3b9fa34f7cf73f4c6276783614a1a0fd.class",
            "sha1" : "6867f45c3b9fa34f7cf73f4c6276783614a1a0fd",
            "size" : 137642,
            "translated" : 965,
            "fuzzy" : 43,
            "untranslated" : 106
        },
        "pt_BR" : {
            "file" : "12f1ce6a37db8a7cbbaf2bf8461a0ea9da139a81.class",
            "sha1" : "12f1ce6a37db8a7cbbaf2bf8461a0ea9da139a81",
            "size" : 141663,
            "translated" : 998,
            "fuzzy" : 43,
            "untranslated" : 73
        },
        "ro" : {
            "file" : "791bc182e6700951e7e4d14899fda7002dceb6f0.class",
            "sha1" : "791bc182e6700951e7e4d14899fda7002dceb6f0",
            "size" : 59143,
            "translated" : 428,
            "fuzzy" : 82,
            "untranslated" : 604
        },
        "ru" : {
            "file" : "ead128dba8c0430397ae22fd051bfb76d2e4e567.class",
            "sha1" : "ead128dba8c0430397ae22fd051bfb76d2e4e567",
            "size" : 150706,
            "translated" : 1084,
            "fuzzy" : 25,
            "untranslated" : 5
        },
        "si" : {
            "file" : "c734b0b209dbff728932df65eb4f1b0f4c5eabdd.class",
            "sha1" : "c734b0b209dbff728932df65eb4f1b0f4c5eabdd",
            "size" : 1833,
            "translated" : 10,
            "fuzzy" : 19,
            "untranslated" : 1085
        },
        "sk" : {
            "file" : "8d535e757e746f46c59e0b8b354d7d22731cb69f.class",
            "sha1" : "8d535e757e746f46c59e0b8b354d7d22731cb69f",
            "size" : 115612,
            "translated" : 887,
            "fuzzy" : 45,
            "untranslated" : 182
        },
        "sl" : {
            "file" : "7a756d68911a065e15cb7589712278907e9d58e8.class",
            "sha1" : "7a756d68911a065e15cb7589712278907e9d58e8",
            "size" : 20579,
            "translated" : 120,
            "fuzzy" : 58,
            "untranslated" : 936
        },
        "sr" : {
            "file" : "df9be4f178afb47a02977160d6ec511225c64818.class",
            "sha1" : "df9be4f178afb47a02977160d6ec511225c64818",
            "size" : 7068,
            "translated" : 42,
            "fuzzy" : 27,
            "untranslated" : 1045
        },
        "sv" : {
            "file" : "1be56b6282662a484f37d1f39c0c0b879c88af79.class",
            "sha1" : "1be56b6282662a484f37d1f39c0c0b879c88af79",
            "size" : 116949,
            "translated" : 892,
            "fuzzy" : 46,
            "untranslated" : 176
        },
        "th" : {
            "file" : "08e58f696f6dc44fbc010e32ac380e96e9fb4810.class",
            "sha1" : "08e58f696f6dc44fbc010e32ac380e96e9fb4810",
            "size" : 31640,
            "translated" : 256,
            "fuzzy" : 47,
            "untranslated" : 811
        },
        "tr" : {
            "file" : "1f626fa8c9dc644eb9645f3668c6d8e4cbe736d8.class",
            "sha1" : "1f626fa8c9dc644eb9645f3668c6d8e4cbe736d8",
            "size" : 137635,
            "translated" : 998,
            "fuzzy" : 39,
            "untranslated" : 77
        },
        "uk" : {
            "file" : "ca5a012f2c7757e20e7f83161317fd253c9ababd.class",
            "sha1" : "ca5a012f2c7757e20e7f83161317fd253c9ababd",
            "size" : 121049,
            "translated" : 894,
            "fuzzy" : 44,
            "untranslated" : 176
        },
        "vi" : {
            "file" : "fb876379593e743ce3c60d57bdcd376c3d9d81ae.class",
            "sha1" : "fb876379593e743ce3c60d57bdcd376c3d9d81ae",
            "size" : 133283,
            "translated" : 964,
            "fuzzy" : 50,
            "untranslated" : 100
        },
        "zh" : {
            "file" : "42ddae1b010613a7a027d5e28ce0eec0764d2be0.class",
            "sha1" : "42ddae1b010613a7a027d5e28ce0eec0764d2be0",
            "size" : 100375,
            "translated" : 992,
            "fuzzy" : 44,
            "untranslated" : 78
        },
        "zh_TW" : {
            "file" : "5bc1a5690f5acb717ae49ac1ef3ed7cf20464662.class",
            "sha1" : "5bc1a5690f5acb717ae49ac1ef3ed7cf20464662",
            "size" : 96262,
            "translated" : 963,
            "fuzzy" : 48,
            "untranslated" : 103
        }
    }
}
